revisiondict/__init__.py
revisiondict/_version.py
revisiondict/revisiondict.py
revisiondict/unique_revisiondict.py
revisiondict-1.1.0.dist-info/LICENSE
revisiondict-1.1.0.dist-info/METADATA
revisiondict-1.1.0.dist-info/WHEEL
revisiondict-1.1.0.dist-info/top_level.txt
revisiondict-1.1.0.dist-info/RECORD
