Metadata-Version: 2.1
Name: revisiondict
Version: 1.1.0
Summary: RevisionDict works like an ordinary dictionary with additional revision keeping of changes.
Home-page: https://github.com/semiversus/python-revisiondict
Author: Günther Jena
Author-email: guenther@jena.at
License: MIT license
Keywords: dict revision versioning
Classifier: Development Status :: 5 - Production/Stable
Classifier: Intended Audience :: Developers
Classifier: License :: OSI Approved :: MIT License
Classifier: Natural Language :: English
Classifier: Programming Language :: Python :: 3
Classifier: Programming Language :: Python :: 3.5
Classifier: Programming Language :: Python :: 3.6
Classifier: Programming Language :: Python :: 3.7
Classifier: Programming Language :: Python :: 3.8
Classifier: Programming Language :: Python :: 3.9
Classifier: Programming Language :: Python :: 3.10
Classifier: Programming Language :: Python :: 3.11
Classifier: Programming Language :: Python :: 3.12
License-File: LICENSE
